<?xml version="1.0" encoding="utf-8"?><index><stem n="firefox"><phr n="FireFox"><ent r="7" t="1" w="901" /><ent r="7" t="1" w="901" /></phr><phr n="Firefox"><ent r="7" t="132" w="4448" /><ent r="8" t="260" w="1509" /><ent r="7" t="260" w="1868" /><ent r="7" t="260" w="1868" /><ent r="5" t="262" w="64" /><ent r="5" t="262" w="64" /><ent r="5" t="265" w="2138" /><ent r="5" t="265" w="2163" /><ent r="6" t="265" w="2215" /><ent r="6" t="265" w="2215" /><ent r="3" t="361" w="219" /><ent r="5" t="366" w="2848" /><ent r="5" t="366" w="2848" /><ent r="74" t="366" w="2966" /><ent r="74" t="366" w="2966" /><ent r="5" t="366" w="2972" /><ent r="5" t="366" w="2972" /><ent r="5" t="366" w="2991" /><ent r="5" t="366" w="3115" /><ent r="5" t="366" w="3115" /><ent r="5" t="366" w="3145" /><ent r="5" t="366" w="3150" /><ent r="6" t="454" w="91" /><ent r="6" t="454" w="91" /><ent r="5" t="454" w="873" /><ent r="5" t="454" w="873" /><ent r="8" t="454" w="1100" /><ent r="8" t="454" w="1100" /><ent r="3" t="530" w="65" /><ent r="3" t="530" w="65" /><ent r="4" t="553" w="36" /><ent r="4" t="553" w="36" /><ent r="5" t="806" w="138" /><ent r="5" t="806" w="138" /></phr><phr n="firefox"><ent r="69" t="260" w="1527" /><ent r="67" t="260" w="1887" /><ent r="5" t="265" w="2210" /></phr></stem><stem n="address"><phr n="address"><ent r="6" t="1" w="905" /><ent r="6" t="1" w="905" /><ent r="6" t="1" w="934" /><ent r="6" t="1" w="934" /><ent r="5" t="9" w="165" /><ent r="5" t="29" w="122" /><ent r="3" t="46" w="63" /><ent r="3" t="46" w="63" /><ent r="8" t="103" w="503" /><ent r="9" t="103" w="583" /><ent r="8" t="103" w="788" /><ent r="8" t="103" w="795" /><ent r="5" t="123" w="1154" /><ent r="5" t="123" w="1154" /><ent r="8" t="123" w="1232" /><ent r="8" t="123" w="1232" /><ent r="8" t="123" w="1253" /><ent r="8" t="123" w="1253" /><ent r="5" t="132" w="4481" /><ent r="5" t="132" w="4481" /><ent r="5" t="132" w="4493" /><ent r="5" t="132" w="4493" /><ent r="5" t="132" w="4575" /><ent r="7" t="132" w="4838" /><ent r="7" t="132" w="4838" /><ent r="5" t="134" w="724" /><ent r="5" t="134" w="1102" /><ent r="5" t="134" w="1102" /><ent r="9" t="134" w="1138" /><ent r="9" t="134" w="1138" /><ent r="9" t="134" w="1156" /><ent r="8" t="134" w="1171" /><ent r="5" t="134" w="1721" /><ent r="5" t="135" w="248" /><ent r="5" t="135" w="248" /><ent r="8" t="135" w="965" /><ent r="8" t="135" w="965" /><ent r="5" t="137" w="328" /><ent r="5" t="138" w="284" /><ent r="5" t="138" w="284" /><ent r="3" t="138" w="477" /><ent r="3" t="138" w="477" /><ent r="3" t="138" w="493" /><ent r="3" t="138" w="493" /><ent r="5" t="150" w="924" /><ent r="5" t="150" w="924" /><ent r="5" t="150" w="992" /><ent r="5" t="150" w="992" /><ent r="5" t="150" w="1010" /><ent r="5" t="150" w="1010" /><ent r="5" t="165" w="840" /><ent r="5" t="165" w="840" /><ent r="5" t="165" w="998" /><ent r="5" t="165" w="998" /><ent r="11" t="184" w="1063" /><ent r="11" t="184" w="1063" /><ent r="11" t="184" w="1067" /><ent r="11" t="184" w="1067" /><ent r="10" t="184" w="3342" /><ent r="10" t="184" w="3342" /><ent r="5" t="187" w="29" /><ent r="5" t="187" w="29" /><ent r="5" t="187" w="53" /><ent r="5" t="187" w="53" /><ent r="7" t="187" w="83" /><ent r="7" t="187" w="83" /><ent r="7" t="187" w="96" /><ent r="7" t="187" w="96" /><ent r="5" t="187" w="396" /><ent r="5" t="187" w="396" /><ent r="10" t="187" w="1145" /><ent r="10" t="187" w="1163" /><ent r="10" t="187" w="1183" /><ent r="5" t="189" w="94" /><ent r="5" t="189" w="94" /><ent r="8" t="215" w="110" /><ent r="8" t="215" w="110" /><ent r="8" t="215" w="142" /><ent r="8" t="215" w="142" /><ent r="10" t="227" w="357" /><ent r="10" t="227" w="357" /><ent r="8" t="228" w="179" /><ent r="8" t="228" w="179" /><ent r="6" t="245" w="323" /><ent r="6" t="245" w="323" /><ent r="108" t="245" w="332" /><ent r="108" t="245" w="332" /><ent r="7" t="256" w="215" /><ent r="7" t="256" w="215" /><ent r="5" t="256" w="387" /><ent r="5" t="256" w="387" /><ent r="10" t="269" w="358" /><ent r="10" t="269" w="358" /><ent r="100" t="288" w="5" /><ent r="100" t="288" w="5" /><ent r="3" t="304" w="434" /><ent r="3" t="304" w="434" /><ent r="5" t="323" w="97" /><ent r="5" t="323" w="97" /><ent r="10" t="339" w="296" /><ent r="10" t="339" w="301" /><ent r="10" t="339" w="301" /><ent r="11" t="340" w="945" /><ent r="11" t="340" w="945" /><ent r="10" t="343" w="528" /><ent r="10" t="343" w="618" /><ent r="10" t="343" w="618" /><ent r="10" t="348" w="233" /><ent r="10" t="348" w="237" /><ent r="10" t="348" w="237" /><ent r="4" t="352" w="259" /><ent r="4" t="352" w="259" /><ent r="11" t="352" w="717" /><ent r="11" t="352" w="717" /><ent r="8" t="352" w="1018" /><ent r="8" t="352" w="1018" /><ent r="7" t="352" w="2218" /><ent r="11" t="363" w="399" /><ent r="11" t="363" w="399" /><ent r="5" t="366" w="2995" /><ent r="5" t="366" w="2995" /><ent r="9" t="396" w="58" /><ent r="9" t="396" w="58" /><ent r="9" t="396" w="238" /><ent r="9" t="396" w="238" /><ent r="9" t="396" w="485" /><ent r="9" t="396" w="485" /><ent r="9" t="396" w="518" /><ent r="9" t="396" w="518" /><ent r="9" t="396" w="817" /><ent r="9" t="396" w="817" /><ent r="4" t="399" w="79" /><ent r="4" t="399" w="79" /><ent r="3" t="399" w="988" /><ent r="3" t="399" w="988" /><ent r="3" t="399" w="991" /><ent r="3" t="399" w="991" /><ent r="6" t="400" w="949" /><ent r="6" t="400" w="949" /><ent r="5" t="400" w="1130" /><ent r="5" t="400" w="1130" /><ent r="6" t="402" w="806" /><ent r="6" t="402" w="806" /><ent r="8" t="405" w="3667" /><ent r="8" t="405" w="3667" /><ent r="8" t="405" w="3673" /><ent r="8" t="405" w="3673" /><ent r="5" t="405" w="3777" /><ent r="5" t="405" w="3777" /><ent r="3" t="406" w="25" /><ent r="3" t="406" w="25" /><ent r="9" t="411" w="563" /><ent r="9" t="411" w="563" /><ent r="8" t="414" w="233" /><ent r="8" t="414" w="233" /><ent r="5" t="423" w="597" /><ent r="5" t="423" w="597" /><ent r="8" t="424" w="223" /><ent r="8" t="424" w="223" /><ent r="3" t="437" w="190" /><ent r="3" t="437" w="190" /><ent r="10" t="438" w="148" /><ent r="12" t="438" w="215" /><ent r="12" t="438" w="222" /><ent r="10" t="438" w="294" /><ent r="10" t="438" w="294" /><ent r="10" t="438" w="686" /><ent r="10" t="438" w="686" /><ent r="5" t="445" w="372" /><ent r="5" t="445" w="393" /><ent r="5" t="445" w="393" /><ent r="3" t="449" w="191" /><ent r="3" t="449" w="191" /><ent r="3" t="449" w="198" /><ent r="3" t="449" w="198" /><ent r="3" t="449" w="214" /><ent r="6" t="454" w="1611" /><ent r="6" t="454" w="1611" /><ent r="5" t="456" w="1303" /><ent r="5" t="456" w="1369" /><ent r="5" t="456" w="1369" /><ent r="9" t="458" w="166" /><ent r="9" t="458" w="166" /><ent r="10" t="460" w="488" /><ent r="10" t="460" w="488" /><ent r="10" t="460" w="602" /><ent r="10" t="460" w="602" /><ent r="7" t="460" w="2941" /><ent r="7" t="460" w="2941" /><ent r="7" t="469" w="273" /><ent r="7" t="469" w="273" /><ent r="8" t="470" w="1495" /><ent r="8" t="470" w="1495" /><ent r="13" t="491" w="517" /><ent r="13" t="491" w="517" /><ent r="13" t="491" w="548" /><ent r="13" t="491" w="548" /><ent r="12" t="491" w="580" /><ent r="12" t="491" w="580" /><ent r="11" t="493" w="199" /><ent r="11" t="493" w="199" /><ent r="11" t="493" w="948" /><ent r="11" t="493" w="948" /><ent r="11" t="495" w="277" /><ent r="11" t="495" w="277" /><ent r="3" t="508" w="98" /><ent r="3" t="508" w="98" /><ent r="7" t="508" w="359" /><ent r="7" t="508" w="359" /><ent r="7" t="508" w="370" /><ent r="7" t="508" w="370" /><ent r="6" t="509" w="63" /><ent r="6" t="509" w="63" /><ent r="6" t="509" w="231" /><ent r="7" t="509" w="243" /><ent r="7" t="509" w="243" /><ent r="6" t="509" w="297" /><ent r="6" t="509" w="388" /><ent r="6" t="509" w="402" /><ent r="12" t="511" w="404" /><ent r="12" t="511" w="404" /><ent r="3" t="517" w="20" /><ent r="3" t="518" w="115" /><ent r="3" t="518" w="120" /><ent r="3" t="518" w="120" /><ent r="10" t="519" w="271" /><ent r="10" t="519" w="319" /><ent r="10" t="519" w="328" /><ent r="10" t="519" w="363" /><ent r="10" t="520" w="278" /><ent r="10" t="520" w="278" /><ent r="10" t="520" w="300" /><ent r="10" t="520" w="380" /><ent r="10" t="520" w="630" /><ent r="10" t="520" w="630" /><ent r="11" t="520" w="668" /><ent r="10" t="520" w="930" /><ent r="10" t="520" w="930" /><ent r="13" t="520" w="1434" /><ent r="13" t="520" w="1434" /><ent r="13" t="520" w="1441" /><ent r="13" t="520" w="1441" /><ent r="13" t="520" w="1491" /><ent r="13" t="520" w="1491" /><ent r="5" t="520" w="3218" /><ent r="5" t="520" w="3218" /><ent r="10" t="522" w="177" /><ent r="10" t="522" w="177" /><ent r="10" t="522" w="371" /><ent r="100" t="524" w="7" /><ent r="100" t="524" w="7" /><ent r="3" t="524" w="16" /><ent r="3" t="524" w="16" /><ent r="3" t="524" w="56" /><ent r="3" t="524" w="56" /><ent r="3" t="524" w="80" /><ent r="3" t="524" w="80" /><ent r="5" t="524" w="217" /><ent r="100" t="524" w="245" /><ent r="100" t="524" w="245" /><ent r="5" t="524" w="288" /><ent r="5" t="524" w="288" /><ent r="7" t="524" w="312" /><ent r="7" t="524" w="312" /><ent r="7" t="524" w="318" /><ent r="5" t="524" w="424" /><ent r="5" t="524" w="424" /><ent r="5" t="524" w="538" /><ent r="5" t="524" w="538" /><ent r="5" t="524" w="549" /><ent r="5" t="524" w="549" /><ent r="5" t="524" w="586" /><ent r="5" t="524" w="586" /><ent r="5" t="525" w="751" /><ent r="5" t="525" w="751" /><ent r="3" t="526" w="179" /><ent r="5" t="528" w="106" /><ent r="5" t="528" w="106" /><ent r="6" t="528" w="472" /><ent r="6" t="528" w="472" /><ent r="8" t="528" w="775" /><ent r="8" t="528" w="775" /><ent r="5" t="529" w="168" /><ent r="5" t="529" w="168" /><ent r="12" t="546" w="600" /><ent r="12" t="546" w="600" /><ent r="12" t="546" w="609" /><ent r="3" t="548" w="47" /><ent r="3" t="548" w="47" /><ent r="5" t="548" w="1797" /><ent r="5" t="548" w="1797" /><ent r="6" t="551" w="99" /><ent r="6" t="551" w="99" /><ent r="3" t="587" w="14" /><ent r="3" t="587" w="14" /><ent r="3" t="587" w="86" /><ent r="3" t="587" w="86" /><ent r="3" t="587" w="133" /><ent r="3" t="587" w="133" /><ent r="4" t="673" w="40" /><ent r="3" t="673" w="169" /><ent r="3" t="695" w="118" /><ent r="3" t="695" w="118" /><ent r="3" t="699" w="130" /><ent r="3" t="699" w="130" /><ent r="6" t="737" w="91" /><ent r="6" t="737" w="91" /><ent r="6" t="737" w="107" /><ent r="6" t="737" w="107" /><ent r="6" t="737" w="123" /><ent r="6" t="737" w="123" /><ent r="3" t="772" w="97" /><ent r="3" t="772" w="97" /><ent r="7" t="772" w="188" /><ent r="7" t="772" w="188" /><ent r="7" t="772" w="214" /><ent r="7" t="772" w="219" /><ent r="7" t="772" w="219" /><ent r="6" t="804" w="197" /><ent r="6" t="804" w="218" /></phr><phr n="Address"><ent r="8" t="103" w="499" /><ent r="8" t="103" w="499" /><ent r="8" t="103" w="579" /><ent r="8" t="103" w="579" /><ent r="8" t="103" w="784" /><ent r="8" t="103" w="784" /><ent r="8" t="103" w="791" /><ent r="8" t="103" w="791" /><ent r="8" t="132" w="643" /><ent r="8" t="132" w="643" /><ent r="67" t="132" w="4665" /><ent r="67" t="132" w="4665" /><ent r="74" t="132" w="4757" /><ent r="74" t="132" w="4757" /><ent r="8" t="132" w="4843" /><ent r="8" t="132" w="4843" /><ent r="8" t="132" w="4849" /><ent r="8" t="132" w="4849" /><ent r="8" t="132" w="4883" /><ent r="8" t="132" w="4883" /><ent r="8" t="132" w="4889" /><ent r="8" t="132" w="4889" /><ent r="66" t="132" w="5015" /><ent r="66" t="132" w="5015" /><ent r="8" t="134" w="1135" /><ent r="8" t="134" w="1135" /><ent r="8" t="135" w="961" /><ent r="8" t="135" w="961" /><ent r="8" t="172" w="1766" /><ent r="6" t="185" w="116" /><ent r="6" t="185" w="116" /><ent r="5" t="187" w="15" /><ent r="5" t="187" w="15" /><ent r="5" t="187" w="126" /><ent r="5" t="187" w="126" /><ent r="7" t="187" w="355" /><ent r="7" t="187" w="355" /><ent r="10" t="187" w="1153" /><ent r="10" t="187" w="1153" /><ent r="8" t="215" w="106" /><ent r="8" t="215" w="106" /><ent r="8" t="215" w="138" /><ent r="8" t="215" w="138" /><ent r="7" t="245" w="326" /><ent r="7" t="245" w="326" /><ent r="68" t="245" w="343" /><ent r="68" t="245" w="343" /><ent r="13" t="284" w="1339" /><ent r="13" t="284" w="1339" /><ent r="13" t="284" w="1344" /><ent r="13" t="284" w="1344" /><ent r="5" t="288" w="44" /><ent r="5" t="288" w="44" /><ent r="106" t="288" w="54" /><ent r="106" t="288" w="54" /><ent r="10" t="288" w="75" /><ent r="10" t="288" w="75" /><ent r="10" t="288" w="108" /><ent r="10" t="288" w="108" /><ent r="3" t="304" w="408" /><ent r="3" t="305" w="91" /><ent r="3" t="305" w="91" /><ent r="11" t="307" w="756" /><ent r="11" t="307" w="756" /><ent r="11" t="307" w="810" /><ent r="11" t="307" w="810" /><ent r="7" t="347" w="783" /><ent r="7" t="347" w="1079" /><ent r="109" t="396" w="1131" /><ent r="109" t="396" w="1131" /><ent r="8" t="405" w="3663" /><ent r="8" t="405" w="3663" /><ent r="12" t="438" w="210" /><ent r="10" t="438" w="289" /><ent r="10" t="438" w="289" /><ent r="5" t="456" w="1386" /><ent r="5" t="456" w="1386" /><ent r="5" t="456" w="1397" /><ent r="5" t="456" w="1399" /><ent r="5" t="456" w="1401" /><ent r="12" t="491" w="575" /><ent r="12" t="491" w="575" /><ent r="11" t="493" w="943" /><ent r="11" t="493" w="943" /><ent r="4" t="508" w="71" /><ent r="4" t="508" w="71" /><ent r="10" t="519" w="358" /><ent r="10" t="519" w="358" /><ent r="10" t="520" w="274" /><ent r="10" t="520" w="274" /><ent r="6" t="520" w="3310" /><ent r="6" t="520" w="3310" /><ent r="10" t="522" w="172" /><ent r="10" t="522" w="172" /><ent r="1000" t="524" w="3" /><ent r="1000" t="524" w="3" /><ent r="102" t="524" w="12" /><ent r="102" t="524" w="12" /><ent r="6" t="524" w="158" /><ent r="6" t="524" w="158" /><ent r="5" t="524" w="251" /><ent r="5" t="524" w="251" /><ent r="6" t="524" w="292" /><ent r="6" t="524" w="292" /><ent r="5" t="524" w="429" /><ent r="5" t="524" w="429" /><ent r="5" t="524" w="564" /><ent r="5" t="524" w="564" /><ent r="4" t="526" w="120" /><ent r="4" t="526" w="120" /><ent r="8" t="533" w="156" /><ent r="8" t="533" w="156" /><ent r="8" t="533" w="163" /><ent r="8" t="533" w="163" /><ent r="8" t="533" w="170" /><ent r="8" t="533" w="170" /><ent r="8" t="533" w="234" /><ent r="8" t="533" w="234" /><ent r="8" t="533" w="241" /><ent r="8" t="533" w="241" /><ent r="8" t="533" w="248" /><ent r="8" t="533" w="248" /><ent r="8" t="533" w="312" /><ent r="8" t="533" w="312" /><ent r="8" t="533" w="322" /><ent r="8" t="533" w="322" /><ent r="8" t="533" w="329" /><ent r="8" t="533" w="329" /><ent r="6" t="555" w="317" /><ent r="6" t="555" w="317" /><ent r="107" t="737" w="95" /><ent r="107" t="737" w="95" /><ent r="107" t="737" w="111" /><ent r="107" t="737" w="111" /><ent r="107" t="737" w="134" /><ent r="107" t="737" w="134" /><ent r="6" t="752" w="84" /><ent r="6" t="752" w="84" /><ent r="6" t="752" w="86" /><ent r="6" t="752" w="86" /><ent r="6" t="752" w="92" /><ent r="6" t="752" w="97" /><ent r="6" t="752" w="97" /><ent r="6" t="752" w="103" /><ent r="6" t="752" w="112" /><ent r="6" t="752" w="121" /><ent r="6" t="752" w="3161" /><ent r="6" t="752" w="3161" /><ent r="8" t="772" w="208" /><ent r="8" t="772" w="208" /><ent r="8" t="772" w="242" /><ent r="8" t="772" w="242" /><ent r="6" t="806" w="106" /><ent r="6" t="806" w="106" /><ent r="67" t="810" w="521" /><ent r="67" t="810" w="521" /></phr><phr n="addresses"><ent r="6" t="132" w="4655" /><ent r="6" t="132" w="4655" /><ent r="6" t="132" w="4676" /><ent r="6" t="132" w="4676" /><ent r="5" t="134" w="1743" /><ent r="5" t="134" w="1743" /><ent r="5" t="135" w="912" /><ent r="5" t="135" w="912" /><ent r="3" t="136" w="133" /><ent r="3" t="136" w="133" /><ent r="5" t="136" w="286" /><ent r="5" t="136" w="286" /><ent r="9" t="136" w="499" /><ent r="9" t="136" w="499" /><ent r="9" t="136" w="510" /><ent r="9" t="136" w="510" /><ent r="3" t="138" w="1254" /><ent r="3" t="138" w="1254" /><ent r="8" t="172" w="1778" /><ent r="8" t="172" w="1778" /><ent r="8" t="172" w="1800" /><ent r="8" t="172" w="1800" /><ent r="5" t="194" w="636" /><ent r="10" t="227" w="371" /><ent r="10" t="227" w="371" /><ent r="8" t="228" w="193" /><ent r="8" t="228" w="193" /><ent r="7" t="245" w="286" /><ent r="7" t="245" w="286" /><ent r="7" t="245" w="338" /><ent r="7" t="256" w="230" /><ent r="7" t="256" w="230" /><ent r="10" t="260" w="1398" /><ent r="7" t="264" w="135" /><ent r="7" t="264" w="135" /><ent r="3" t="304" w="445" /><ent r="3" t="304" w="448" /><ent r="3" t="399" w="354" /><ent r="3" t="399" w="354" /><ent r="3" t="399" w="971" /><ent r="3" t="399" w="971" /><ent r="10" t="445" w="334" /><ent r="5" t="445" w="382" /><ent r="5" t="456" w="1380" /><ent r="5" t="456" w="1380" /><ent r="10" t="522" w="220" /><ent r="3" t="524" w="35" /><ent r="3" t="524" w="42" /><ent r="3" t="524" w="42" /><ent r="7" t="524" w="364" /><ent r="7" t="524" w="364" /><ent r="5" t="524" w="380" /><ent r="5" t="524" w="380" /><ent r="5" t="524" w="419" /><ent r="5" t="524" w="419" /><ent r="3" t="762" w="80" /><ent r="3" t="762" w="80" /><ent r="6" t="768" w="281" /><ent r="7" t="772" w="221" /><ent r="7" t="772" w="221" /><ent r="7" t="772" w="248" /><ent r="7" t="772" w="264" /><ent r="7" t="772" w="264" /><ent r="6" t="772" w="283" /><ent r="6" t="772" w="283" /><ent r="7" t="773" w="87" /><ent r="7" t="773" w="87" /></phr><phr n="addressed"><ent r="9" t="378" w="243" /><ent r="10" t="520" w="623" /><ent r="10" t="520" w="623" /><ent r="13" t="520" w="1455" /><ent r="13" t="520" w="1455" /></phr><phr n="Addresses"><ent r="6" t="524" w="165" /><ent r="6" t="524" w="165" /><ent r="6" t="524" w="299" /><ent r="6" t="524" w="299" /><ent r="5" t="524" w="306" /><ent r="5" t="524" w="306" /><ent r="4" t="526" w="127" /><ent r="4" t="526" w="127" /></phr></stem><stem n="secur"><phr n="Security"><ent r="7" t="1" w="910" /><ent r="7" t="1" w="910" /><ent r="7" t="1" w="939" /><ent r="7" t="1" w="939" /><ent r="1000" t="58" w="3" /><ent r="1000" t="58" w="3" /><ent r="102" t="58" w="12" /><ent r="102" t="58" w="12" /><ent r="9" t="132" w="4417" /><ent r="9" t="132" w="4417" /><ent r="10" t="187" w="1117" /><ent r="10" t="187" w="1117" /><ent r="6" t="232" w="105" /><ent r="6" t="232" w="105" /><ent r="66" t="260" w="563" /><ent r="66" t="260" w="563" /><ent r="10" t="260" w="1967" /><ent r="10" t="260" w="1967" /><ent r="8" t="260" w="2167" /><ent r="8" t="260" w="2167" /><ent r="5" t="260" w="2254" /><ent r="5" t="260" w="2254" /><ent r="6" t="265" w="2293" /><ent r="6" t="265" w="2293" /><ent r="6" t="280" w="175" /><ent r="6" t="280" w="175" /><ent r="1000" t="358" w="2" /><ent r="1000" t="358" w="2" /><ent r="102" t="358" w="11" /><ent r="102" t="358" w="11" /><ent r="5" t="359" w="91" /><ent r="5" t="359" w="91" /><ent r="5" t="359" w="663" /><ent r="5" t="359" w="663" /><ent r="1000" t="360" w="1" /><ent r="1000" t="360" w="1" /><ent r="102" t="360" w="11" /><ent r="102" t="360" w="11" /><ent r="5" t="362" w="69" /><ent r="5" t="362" w="69" /><ent r="6" t="362" w="3070" /><ent r="6" t="362" w="3070" /><ent r="7" t="366" w="26" /><ent r="7" t="366" w="26" /><ent r="5" t="366" w="201" /><ent r="5" t="366" w="201" /><ent r="5" t="366" w="217" /><ent r="5" t="366" w="217" /><ent r="5" t="366" w="768" /><ent r="5" t="366" w="854" /><ent r="5" t="366" w="854" /><ent r="5" t="366" w="868" /><ent r="5" t="366" w="868" /><ent r="6" t="366" w="876" /><ent r="6" t="366" w="876" /><ent r="6" t="366" w="889" /><ent r="6" t="366" w="889" /><ent r="6" t="366" w="900" /><ent r="6" t="366" w="900" /><ent r="6" t="366" w="908" /><ent r="6" t="366" w="908" /><ent r="6" t="366" w="925" /><ent r="6" t="366" w="925" /><ent r="6" t="366" w="944" /><ent r="6" t="366" w="944" /><ent r="5" t="366" w="956" /><ent r="5" t="366" w="956" /><ent r="5" t="366" w="1087" /><ent r="5" t="366" w="1087" /><ent r="74" t="366" w="1185" /><ent r="74" t="366" w="1185" /><ent r="5" t="366" w="1193" /><ent r="5" t="366" w="1193" /><ent r="5" t="366" w="1231" /><ent r="5" t="366" w="1231" /><ent r="5" t="366" w="1389" /><ent r="5" t="366" w="1389" /><ent r="74" t="366" w="1430" /><ent r="74" t="366" w="1430" /><ent r="66" t="366" w="1460" /><ent r="66" t="366" w="1460" /><ent r="5" t="366" w="1505" /><ent r="5" t="366" w="1505" /><ent r="6" t="366" w="1526" /><ent r="6" t="366" w="1526" /><ent r="5" t="366" w="1705" /><ent r="5" t="366" w="1705" /><ent r="5" t="366" w="1788" /><ent r="5" t="366" w="1788" /><ent r="5" t="366" w="1844" /><ent r="5" t="366" w="1844" /><ent r="6" t="366" w="1920" /><ent r="6" t="366" w="1920" /><ent r="6" t="366" w="2014" /><ent r="6" t="366" w="2014" /><ent r="5" t="366" w="2228" /><ent r="5" t="366" w="2228" /><ent r="5" t="366" w="2238" /><ent r="5" t="366" w="2238" /><ent r="5" t="366" w="2413" /><ent r="5" t="366" w="2413" /><ent r="5" t="366" w="2421" /><ent r="5" t="366" w="2421" /><ent r="5" t="366" w="2510" /><ent r="5" t="366" w="2510" /><ent r="5" t="366" w="2562" /><ent r="5" t="366" w="2562" /><ent r="66" t="366" w="2572" /><ent r="66" t="366" w="2572" /><ent r="5" t="366" w="2613" /><ent r="5" t="366" w="2613" /><ent r="5" t="366" w="2703" /><ent r="5" t="366" w="2711" /><ent r="5" t="366" w="2711" /><ent r="5" t="366" w="2826" /><ent r="5" t="366" w="2826" /><ent r="5" t="366" w="2885" /><ent r="5" t="366" w="2885" /><ent r="7" t="366" w="2914" /><ent r="7" t="366" w="2914" /><ent r="5" t="366" w="2930" /><ent r="5" t="366" w="2930" /><ent r="7" t="366" w="3245" /><ent r="7" t="366" w="3245" /><ent r="9" t="390" w="2278" /><ent r="9" t="390" w="2278" /><ent r="12" t="390" w="2289" /><ent r="12" t="390" w="2289" /><ent r="12" t="390" w="2328" /><ent r="12" t="390" w="2328" /><ent r="12" t="390" w="2340" /><ent r="12" t="390" w="2340" /><ent r="5" t="441" w="841" /><ent r="5" t="441" w="841" /><ent r="66" t="441" w="861" /><ent r="66" t="441" w="861" /><ent r="10" t="454" w="1137" /><ent r="10" t="454" w="1137" /><ent r="9" t="462" w="771" /><ent r="9" t="462" w="771" /><ent r="8" t="470" w="1898" /><ent r="8" t="470" w="1898" /><ent r="13" t="491" w="1640" /><ent r="13" t="491" w="1640" /><ent r="6" t="752" w="6305" /><ent r="6" t="752" w="6305" /><ent r="7" t="797" w="640" /><ent r="7" t="797" w="640" /><ent r="7" t="797" w="1381" /><ent r="7" t="797" w="1381" /><ent r="6" t="806" w="251" /><ent r="6" t="806" w="251" /><ent r="6" t="806" w="429" /><ent r="6" t="806" w="429" /><ent r="6" t="806" w="614" /><ent r="6" t="806" w="614" /><ent r="6" t="806" w="702" /><ent r="6" t="806" w="702" /><ent r="67" t="810" w="39" /><ent r="67" t="810" w="39" /></phr><phr n="security"><ent r="6" t="26" w="723" /><ent r="6" t="26" w="723" /><ent r="6" t="26" w="743" /><ent r="6" t="26" w="743" /><ent r="6" t="90" w="160" /><ent r="6" t="90" w="160" /><ent r="10" t="132" w="543" /><ent r="10" t="132" w="543" /><ent r="3" t="162" w="175" /><ent r="3" t="162" w="175" /><ent r="10" t="187" w="1127" /><ent r="10" t="187" w="1127" /><ent r="5" t="208" w="319" /><ent r="5" t="208" w="319" /><ent r="3" t="219" w="256" /><ent r="3" t="219" w="293" /><ent r="100" t="260" w="15" /><ent r="5" t="260" w="557" /><ent r="5" t="260" w="557" /><ent r="6" t="260" w="1937" /><ent r="6" t="260" w="1937" /><ent r="5" t="265" w="2270" /><ent r="5" t="265" w="2270" /><ent r="11" t="283" w="1332" /><ent r="11" t="283" w="1332" /><ent r="7" t="283" w="1575" /><ent r="7" t="283" w="1575" /><ent r="8" t="295" w="1896" /><ent r="6" t="347" w="41" /><ent r="6" t="347" w="41" /><ent r="100" t="358" w="4" /><ent r="100" t="358" w="8" /><ent r="100" t="358" w="8" /><ent r="100" t="359" w="3" /><ent r="100" t="359" w="15" /><ent r="100" t="359" w="15" /><ent r="3" t="359" w="19" /><ent r="3" t="359" w="19" /><ent r="3" t="359" w="22" /><ent r="3" t="359" w="22" /><ent r="5" t="359" w="155" /><ent r="5" t="359" w="155" /><ent r="100" t="360" w="4" /><ent r="100" t="361" w="3" /><ent r="3" t="361" w="128" /><ent r="5" t="362" w="218" /><ent r="5" t="362" w="218" /><ent r="5" t="362" w="227" /><ent r="5" t="362" w="227" /><ent r="5" t="362" w="306" /><ent r="5" t="362" w="306" /><ent r="5" t="366" w="2949" /><ent r="5" t="366" w="2949" /><ent r="3" t="368" w="68" /><ent r="3" t="368" w="68" /><ent r="8" t="409" w="333" /><ent r="8" t="409" w="333" /><ent r="8" t="412" w="1071" /><ent r="8" t="412" w="1071" /><ent r="8" t="440" w="1208" /><ent r="8" t="440" w="1208" /><ent r="5" t="446" w="87" /><ent r="3" t="447" w="52" /><ent r="4" t="453" w="52" /><ent r="4" t="453" w="52" /><ent r="4" t="453" w="74" /><ent r="4" t="453" w="74" /><ent r="10" t="454" w="1043" /><ent r="10" t="454" w="1043" /><ent r="10" t="460" w="274" /><ent r="10" t="460" w="274" /><ent r="10" t="460" w="298" /><ent r="10" t="460" w="298" /><ent r="10" t="460" w="363" /><ent r="10" t="460" w="363" /><ent r="10" t="460" w="445" /><ent r="10" t="460" w="445" /><ent r="10" t="460" w="542" /><ent r="10" t="460" w="542" /><ent r="10" t="460" w="587" /><ent r="10" t="460" w="587" /><ent r="10" t="460" w="624" /><ent r="10" t="460" w="624" /><ent r="10" t="460" w="665" /><ent r="10" t="460" w="665" /><ent r="10" t="460" w="704" /><ent r="10" t="460" w="704" /><ent r="10" t="460" w="723" /><ent r="10" t="460" w="723" /><ent r="10" t="460" w="750" /><ent r="10" t="460" w="750" /><ent r="10" t="460" w="787" /><ent r="10" t="460" w="787" /><ent r="10" t="460" w="827" /><ent r="10" t="460" w="827" /><ent r="10" t="460" w="938" /><ent r="10" t="460" w="938" /><ent r="10" t="460" w="984" /><ent r="10" t="460" w="984" /><ent r="10" t="460" w="1030" /><ent r="10" t="460" w="1030" /><ent r="10" t="460" w="1138" /><ent r="10" t="460" w="1138" /><ent r="10" t="460" w="1168" /><ent r="10" t="460" w="1168" /><ent r="5" t="469" w="325" /><ent r="5" t="469" w="325" /><ent r="6" t="469" w="383" /><ent r="6" t="469" w="383" /><ent r="100" t="470" w="6" /><ent r="3" t="470" w="148" /><ent r="3" t="470" w="148" /><ent r="7" t="470" w="1389" /><ent r="7" t="470" w="1389" /><ent r="7" t="470" w="1394" /><ent r="7" t="470" w="1394" /><ent r="7" t="470" w="1448" /><ent r="7" t="470" w="1448" /><ent r="10" t="470" w="1457" /><ent r="10" t="470" w="1457" /><ent r="13" t="470" w="1680" /><ent r="13" t="470" w="1680" /><ent r="7" t="470" w="1912" /><ent r="7" t="470" w="1912" /><ent r="5" t="470" w="2541" /><ent r="5" t="470" w="2541" /><ent r="4" t="471" w="70" /><ent r="4" t="471" w="70" /><ent r="10" t="519" w="312" /><ent r="10" t="520" w="401" /><ent r="10" t="520" w="401" /><ent r="9" t="520" w="1692" /><ent r="9" t="520" w="1692" /><ent r="10" t="522" w="352" /><ent r="10" t="522" w="352" /><ent r="10" t="797" w="683" /><ent r="10" t="797" w="683" /><ent r="10" t="797" w="695" /><ent r="10" t="797" w="695" /><ent r="10" t="797" w="1395" /><ent r="10" t="797" w="1395" /><ent r="10" t="797" w="1404" /><ent r="10" t="797" w="1404" /><ent r="8" t="800" w="4325" /><ent r="8" t="800" w="4325" /><ent r="3" t="806" w="44" /><ent r="3" t="806" w="44" /><ent r="8" t="812" w="128" /><ent r="8" t="812" w="128" /></phr><phr n="secure"><ent r="3" t="140" w="141" /><ent r="3" t="140" w="141" /><ent r="10" t="184" w="3330" /><ent r="10" t="184" w="3330" /><ent r="5" t="260" w="2276" /><ent r="5" t="260" w="2276" /><ent r="8" t="343" w="242" /><ent r="8" t="343" w="242" /><ent r="10" t="343" w="544" /><ent r="10" t="343" w="544" /><ent r="10" t="343" w="567" /><ent r="10" t="343" w="567" /><ent r="5" t="347" w="218" /><ent r="5" t="347" w="218" /><ent r="5" t="347" w="451" /><ent r="5" t="347" w="451" /><ent r="10" t="348" w="277" /><ent r="10" t="348" w="277" /><ent r="11" t="352" w="961" /><ent r="11" t="352" w="961" /><ent r="3" t="358" w="24" /><ent r="3" t="358" w="24" /><ent r="5" t="359" w="989" /><ent r="5" t="359" w="989" /><ent r="5" t="359" w="1001" /><ent r="5" t="359" w="1001" /><ent r="5" t="362" w="31" /><ent r="5" t="362" w="31" /><ent r="11" t="363" w="1406" /><ent r="11" t="363" w="1406" /><ent r="6" t="366" w="1548" /><ent r="6" t="366" w="1548" /><ent r="3" t="368" w="84" /><ent r="3" t="399" w="772" /><ent r="3" t="399" w="772" /><ent r="10" t="519" w="305" /><ent r="10" t="519" w="305" /><ent r="3" t="716" w="12" /><ent r="3" t="716" w="12" /><ent r="3" t="716" w="148" /><ent r="3" t="716" w="148" /><ent r="10" t="812" w="1145" /><ent r="10" t="812" w="1145" /></phr><phr n="securely"><ent r="7" t="283" w="1423" /><ent r="7" t="283" w="1567" /><ent r="7" t="283" w="1567" /><ent r="3" t="368" w="52" /><ent r="3" t="368" w="52" /></phr><phr n="Secure"><ent r="6" t="338" w="158" /><ent r="6" t="338" w="158" /><ent r="8" t="343" w="259" /><ent r="8" t="343" w="259" /><ent r="10" t="343" w="539" /><ent r="10" t="343" w="539" /><ent r="8" t="347" w="274" /><ent r="8" t="347" w="274" /><ent r="6" t="347" w="292" /><ent r="6" t="347" w="292" /><ent r="8" t="347" w="507" /><ent r="8" t="347" w="507" /><ent r="6" t="347" w="525" /><ent r="6" t="347" w="525" /><ent r="10" t="348" w="260" /><ent r="10" t="348" w="260" /><ent r="5" t="359" w="328" /><ent r="5" t="359" w="328" /><ent r="5" t="359" w="533" /><ent r="5" t="359" w="533" /><ent r="5" t="359" w="931" /><ent r="5" t="359" w="931" /><ent r="5" t="359" w="1134" /><ent r="5" t="359" w="1134" /><ent r="10" t="362" w="2265" /><ent r="10" t="362" w="2265" /></phr><phr n="secured"><ent r="3" t="358" w="60" /><ent r="3" t="358" w="60" /><ent r="4" t="361" w="85" /><ent r="4" t="361" w="85" /><ent r="9" t="470" w="1068" /><ent r="9" t="470" w="1068" /></phr></stem></index>