<?xml version="1.0" encoding="utf-8"?><index><stem n="cach"><phr n="cached"><ent r="5" t="6" w="148" /><ent r="5" t="6" w="148" /><ent r="5" t="510" w="94" /><ent r="5" t="510" w="94" /><ent r="6" t="510" w="126" /><ent r="6" t="510" w="126" /></phr><phr n="Cache"><ent r="7" t="256" w="239" /><ent r="7" t="256" w="239" /><ent r="5" t="510" w="32" /><ent r="5" t="510" w="32" /><ent r="6" t="510" w="80" /><ent r="6" t="510" w="80" /><ent r="6" t="510" w="85" /><ent r="6" t="510" w="85" /></phr><phr n="caching"><ent r="5" t="365" w="782" /><ent r="5" t="365" w="782" /></phr><phr n="cache"><ent r="5" t="510" w="41" /><ent r="5" t="510" w="41" /><ent r="5" t="510" w="45" /><ent r="6" t="510" w="100" /><ent r="6" t="510" w="100" /><ent r="5" t="510" w="112" /><ent r="5" t="510" w="112" /><ent r="5" t="510" w="142" /><ent r="5" t="510" w="142" /></phr></stem><stem n="either"><phr n="either"><ent r="5" t="6" w="150" /><ent r="5" t="6" w="150" /><ent r="11" t="15" w="174" /><ent r="11" t="15" w="174" /><ent r="3" t="17" w="33" /><ent r="3" t="17" w="33" /><ent r="7" t="19" w="273" /><ent r="7" t="19" w="273" /><ent r="9" t="23" w="491" /><ent r="9" t="23" w="491" /><ent r="3" t="24" w="102" /><ent r="3" t="24" w="102" /><ent r="7" t="24" w="1325" /><ent r="7" t="24" w="1325" /><ent r="7" t="32" w="654" /><ent r="7" t="32" w="654" /><ent r="6" t="36" w="207" /><ent r="6" t="36" w="207" /><ent r="5" t="36" w="269" /><ent r="5" t="36" w="269" /><ent r="5" t="36" w="451" /><ent r="5" t="36" w="451" /><ent r="8" t="57" w="372" /><ent r="8" t="57" w="372" /><ent r="8" t="73" w="432" /><ent r="8" t="73" w="432" /><ent r="8" t="73" w="556" /><ent r="8" t="73" w="556" /><ent r="5" t="73" w="1320" /><ent r="5" t="73" w="1320" /><ent r="5" t="73" w="1518" /><ent r="5" t="73" w="1518" /><ent r="7" t="79" w="1574" /><ent r="7" t="79" w="1574" /><ent r="5" t="84" w="157" /><ent r="5" t="84" w="157" /><ent r="5" t="84" w="326" /><ent r="5" t="84" w="326" /><ent r="5" t="84" w="430" /><ent r="5" t="84" w="430" /><ent r="5" t="114" w="2014" /><ent r="5" t="114" w="2014" /><ent r="3" t="117" w="22" /><ent r="3" t="117" w="22" /><ent r="4" t="118" w="240" /><ent r="4" t="118" w="240" /><ent r="3" t="119" w="124" /><ent r="3" t="119" w="124" /><ent r="3" t="120" w="72" /><ent r="3" t="120" w="72" /><ent r="7" t="124" w="945" /><ent r="7" t="124" w="945" /><ent r="7" t="124" w="1048" /><ent r="7" t="124" w="1048" /><ent r="5" t="129" w="355" /><ent r="5" t="129" w="355" /><ent r="5" t="136" w="60" /><ent r="5" t="136" w="60" /><ent r="5" t="136" w="119" /><ent r="5" t="136" w="119" /><ent r="5" t="136" w="210" /><ent r="5" t="136" w="210" /><ent r="5" t="136" w="261" /><ent r="5" t="136" w="261" /><ent r="5" t="136" w="321" /><ent r="5" t="136" w="321" /><ent r="5" t="136" w="420" /><ent r="5" t="136" w="420" /><ent r="6" t="143" w="89" /><ent r="6" t="143" w="89" /><ent r="5" t="146" w="752" /><ent r="5" t="146" w="752" /><ent r="5" t="152" w="1191" /><ent r="5" t="152" w="1191" /><ent r="5" t="154" w="561" /><ent r="5" t="154" w="561" /><ent r="5" t="157" w="494" /><ent r="5" t="157" w="494" /><ent r="5" t="159" w="424" /><ent r="5" t="159" w="424" /><ent r="10" t="208" w="440" /><ent r="10" t="208" w="440" /><ent r="8" t="209" w="267" /><ent r="8" t="209" w="267" /><ent r="5" t="215" w="908" /><ent r="5" t="215" w="908" /><ent r="3" t="222" w="35" /><ent r="3" t="222" w="35" /><ent r="7" t="237" w="1666" /><ent r="7" t="237" w="1666" /><ent r="5" t="260" w="1993" /><ent r="5" t="260" w="1993" /><ent r="4" t="261" w="64" /><ent r="4" t="261" w="64" /><ent r="4" t="261" w="163" /><ent r="4" t="261" w="163" /><ent r="11" t="275" w="287" /><ent r="11" t="275" w="287" /><ent r="12" t="283" w="744" /><ent r="12" t="283" w="744" /><ent r="12" t="283" w="821" /><ent r="12" t="283" w="821" /><ent r="3" t="286" w="69" /><ent r="3" t="286" w="69" /><ent r="7" t="292" w="777" /><ent r="7" t="292" w="777" /><ent r="7" t="292" w="850" /><ent r="7" t="292" w="850" /><ent r="3" t="293" w="84" /><ent r="3" t="293" w="84" /><ent r="5" t="315" w="305" /><ent r="5" t="315" w="305" /><ent r="10" t="315" w="349" /><ent r="10" t="315" w="349" /><ent r="8" t="319" w="264" /><ent r="8" t="319" w="264" /><ent r="3" t="329" w="96" /><ent r="3" t="329" w="96" /><ent r="5" t="339" w="133" /><ent r="5" t="339" w="133" /><ent r="3" t="343" w="26" /><ent r="3" t="343" w="26" /><ent r="3" t="363" w="750" /><ent r="3" t="363" w="750" /><ent r="3" t="364" w="129" /><ent r="3" t="364" w="129" /><ent r="7" t="369" w="1146" /><ent r="7" t="369" w="1146" /><ent r="5" t="373" w="448" /><ent r="5" t="373" w="448" /><ent r="5" t="386" w="808" /><ent r="5" t="386" w="808" /><ent r="3" t="394" w="91" /><ent r="3" t="394" w="91" /><ent r="5" t="419" w="582" /><ent r="5" t="419" w="582" /><ent r="4" t="451" w="170" /><ent r="4" t="451" w="170" /><ent r="4" t="452" w="136" /><ent r="4" t="452" w="136" /><ent r="3" t="464" w="51" /><ent r="3" t="464" w="51" /><ent r="10" t="482" w="117" /><ent r="10" t="482" w="117" /><ent r="10" t="482" w="334" /><ent r="10" t="482" w="334" /><ent r="5" t="483" w="144" /><ent r="5" t="483" w="144" /><ent r="3" t="486" w="108" /><ent r="3" t="486" w="108" /><ent r="5" t="496" w="690" /><ent r="5" t="496" w="690" /><ent r="5" t="511" w="101" /><ent r="5" t="511" w="101" /><ent r="6" t="514" w="198" /><ent r="6" t="514" w="198" /><ent r="6" t="514" w="231" /><ent r="6" t="514" w="231" /><ent r="6" t="514" w="283" /><ent r="6" t="514" w="283" /><ent r="6" t="514" w="494" /><ent r="6" t="514" w="494" /><ent r="3" t="515" w="27" /><ent r="3" t="515" w="27" /><ent r="5" t="515" w="48" /><ent r="5" t="515" w="48" /><ent r="5" t="515" w="229" /><ent r="5" t="515" w="229" /><ent r="7" t="517" w="257" /><ent r="7" t="517" w="257" /><ent r="7" t="517" w="280" /><ent r="7" t="517" w="280" /><ent r="7" t="517" w="380" /><ent r="7" t="517" w="380" /><ent r="7" t="517" w="403" /><ent r="7" t="517" w="403" /><ent r="3" t="517" w="483" /><ent r="3" t="517" w="483" /><ent r="3" t="517" w="499" /><ent r="3" t="517" w="499" /><ent r="5" t="519" w="101" /><ent r="5" t="519" w="101" /><ent r="3" t="530" w="287" /><ent r="3" t="530" w="287" /><ent r="3" t="567" w="103" /><ent r="3" t="567" w="103" /><ent r="8" t="592" w="243" /><ent r="8" t="592" w="243" /><ent r="5" t="592" w="410" /><ent r="5" t="592" w="410" /><ent r="3" t="618" w="110" /><ent r="3" t="618" w="110" /><ent r="7" t="633" w="245" /><ent r="7" t="633" w="245" /><ent r="7" t="633" w="278" /><ent r="7" t="633" w="278" /><ent r="6" t="650" w="84" /><ent r="6" t="650" w="84" /><ent r="3" t="661" w="80" /><ent r="3" t="661" w="80" /><ent r="3" t="686" w="111" /><ent r="3" t="686" w="111" /><ent r="7" t="689" w="297" /><ent r="7" t="689" w="297" /><ent r="7" t="690" w="84" /><ent r="7" t="690" w="84" /><ent r="6" t="690" w="111" /><ent r="6" t="690" w="111" /><ent r="7" t="707" w="616" /><ent r="7" t="707" w="616" /><ent r="7" t="707" w="5159" /><ent r="7" t="707" w="5159" /><ent r="7" t="707" w="5209" /><ent r="7" t="707" w="5209" /></phr><phr n="Either"><ent r="5" t="84" w="583" /><ent r="5" t="84" w="583" /><ent r="5" t="136" w="519" /><ent r="5" t="136" w="519" /><ent r="5" t="157" w="593" /><ent r="5" t="157" w="593" /><ent r="5" t="187" w="311" /><ent r="5" t="187" w="311" /><ent r="9" t="505" w="359" /><ent r="9" t="505" w="359" /></phr></stem><stem n="fulfil"><phr n="Fulfillment"><ent r="6" t="6" w="161" /><ent r="6" t="6" w="161" /><ent r="4" t="70" w="109" /><ent r="4" t="70" w="109" /><ent r="6" t="165" w="1666" /><ent r="6" t="165" w="1666" /><ent r="8" t="165" w="1693" /><ent r="8" t="165" w="1693" /><ent r="6" t="168" w="2089" /><ent r="6" t="168" w="2089" /><ent r="6" t="174" w="573" /><ent r="6" t="174" w="573" /><ent r="4" t="181" w="180" /><ent r="4" t="181" w="180" /><ent r="4" t="182" w="79" /><ent r="4" t="182" w="79" /><ent r="65" t="182" w="103" /><ent r="65" t="182" w="103" /><ent r="65" t="182" w="129" /><ent r="65" t="182" w="129" /><ent r="7" t="183" w="148" /><ent r="7" t="183" w="148" /><ent r="6" t="183" w="179" /><ent r="6" t="183" w="179" /><ent r="6" t="183" w="480" /><ent r="6" t="183" w="480" /><ent r="1000" t="184" w="1" /><ent r="1000" t="184" w="1" /><ent r="102" t="184" w="9" /><ent r="102" t="184" w="9" /><ent r="5" t="184" w="211" /><ent r="5" t="184" w="211" /><ent r="6" t="184" w="231" /><ent r="6" t="184" w="231" /><ent r="6" t="184" w="243" /><ent r="6" t="184" w="243" /><ent r="6" t="184" w="313" /><ent r="6" t="184" w="313" /><ent r="5" t="184" w="409" /><ent r="5" t="184" w="409" /><ent r="1000" t="185" w="1" /><ent r="1000" t="185" w="1" /><ent r="102" t="185" w="8" /><ent r="102" t="185" w="8" /><ent r="4" t="186" w="170" /><ent r="4" t="186" w="170" /><ent r="6" t="186" w="269" /><ent r="6" t="186" w="269" /><ent r="6" t="186" w="275" /><ent r="6" t="186" w="275" /><ent r="6" t="186" w="570" /><ent r="6" t="186" w="570" /><ent r="4" t="186" w="781" /><ent r="4" t="186" w="781" /><ent r="4" t="186" w="900" /><ent r="4" t="186" w="900" /><ent r="3" t="200" w="71" /><ent r="3" t="200" w="71" /><ent r="3" t="381" w="86" /><ent r="3" t="381" w="86" /><ent r="6" t="386" w="755" /><ent r="6" t="386" w="755" /><ent r="7" t="410" w="388" /><ent r="7" t="410" w="388" /><ent r="68" t="410" w="393" /><ent r="68" t="410" w="393" /><ent r="4" t="454" w="135" /><ent r="4" t="454" w="135" /><ent r="6" t="671" w="4153" /><ent r="6" t="671" w="4153" /><ent r="6" t="671" w="4162" /><ent r="6" t="671" w="4162" /><ent r="6" t="671" w="4172" /><ent r="6" t="671" w="4172" /><ent r="6" t="671" w="4183" /><ent r="6" t="671" w="4183" /><ent r="6" t="671" w="4194" /><ent r="6" t="671" w="4194" /><ent r="6" t="671" w="6033" /><ent r="6" t="671" w="6033" /><ent r="6" t="717" w="537" /><ent r="6" t="717" w="537" /><ent r="6" t="717" w="549" /><ent r="6" t="717" w="549" /><ent r="65" t="723" w="86" /><ent r="65" t="723" w="86" /></phr><phr n="fulfilled"><ent r="5" t="60" w="267" /><ent r="5" t="71" w="258" /><ent r="10" t="73" w="1224" /><ent r="10" t="73" w="1246" /><ent r="5" t="129" w="208" /><ent r="6" t="129" w="463" /><ent r="6" t="129" w="463" /><ent r="5" t="163" w="260" /><ent r="6" t="172" w="182" /><ent r="6" t="172" w="182" /><ent r="6" t="172" w="193" /><ent r="6" t="172" w="193" /><ent r="6" t="174" w="568" /><ent r="6" t="174" w="568" /><ent r="5" t="175" w="825" /><ent r="5" t="175" w="989" /><ent r="5" t="175" w="989" /><ent r="5" t="175" w="2151" /><ent r="5" t="177" w="651" /><ent r="5" t="180" w="513" /><ent r="5" t="180" w="513" /><ent r="5" t="180" w="592" /><ent r="5" t="180" w="592" /><ent r="5" t="180" w="900" /><ent r="5" t="180" w="900" /><ent r="3" t="181" w="111" /><ent r="3" t="185" w="73" /><ent r="3" t="186" w="857" /><ent r="4" t="189" w="26" /><ent r="4" t="189" w="26" /><ent r="4" t="189" w="46" /><ent r="4" t="189" w="46" /><ent r="4" t="189" w="119" /><ent r="4" t="189" w="119" /><ent r="3" t="386" w="69" /><ent r="3" t="386" w="69" /><ent r="3" t="450" w="246" /><ent r="9" t="715" w="1272" /></phr><phr n="fulfill"><ent r="3" t="68" w="85" /><ent r="3" t="68" w="85" /><ent r="3" t="71" w="22" /><ent r="3" t="71" w="22" /><ent r="3" t="71" w="63" /><ent r="3" t="71" w="63" /><ent r="5" t="129" w="807" /><ent r="5" t="129" w="807" /><ent r="6" t="131" w="74" /><ent r="6" t="131" w="74" /><ent r="4" t="182" w="170" /><ent r="4" t="182" w="170" /><ent r="5" t="182" w="179" /><ent r="5" t="182" w="179" /><ent r="10" t="183" w="703" /><ent r="3" t="184" w="27" /><ent r="3" t="184" w="27" /><ent r="3" t="186" w="25" /><ent r="3" t="186" w="25" /><ent r="5" t="186" w="321" /><ent r="5" t="186" w="321" /><ent r="10" t="194" w="996" /><ent r="10" t="194" w="996" /><ent r="10" t="201" w="533" /><ent r="10" t="201" w="533" /><ent r="10" t="202" w="349" /><ent r="10" t="202" w="349" /><ent r="3" t="453" w="49" /><ent r="3" t="453" w="49" /></phr><phr n="fulfillment"><ent r="3" t="68" w="98" /><ent r="3" t="68" w="98" /><ent r="5" t="68" w="294" /><ent r="5" t="68" w="294" /><ent r="9" t="73" w="1267" /><ent r="9" t="73" w="1267" /><ent r="5" t="129" w="247" /><ent r="5" t="129" w="247" /><ent r="5" t="129" w="544" /><ent r="5" t="129" w="544" /><ent r="3" t="165" w="148" /><ent r="3" t="165" w="148" /><ent r="5" t="165" w="1679" /><ent r="5" t="165" w="1679" /><ent r="8" t="165" w="1696" /><ent r="8" t="165" w="1696" /><ent r="9" t="165" w="1744" /><ent r="9" t="165" w="1744" /><ent r="9" t="165" w="1760" /><ent r="9" t="165" w="1760" /><ent r="8" t="168" w="458" /><ent r="6" t="172" w="165" /><ent r="6" t="172" w="165" /><ent r="6" t="172" w="235" /><ent r="6" t="172" w="235" /><ent r="5" t="180" w="528" /><ent r="5" t="180" w="528" /><ent r="4" t="181" w="139" /><ent r="4" t="181" w="139" /><ent r="4" t="181" w="172" /><ent r="4" t="181" w="172" /><ent r="4" t="181" w="177" /><ent r="4" t="181" w="177" /><ent r="4" t="181" w="184" /><ent r="4" t="181" w="184" /><ent r="4" t="181" w="191" /><ent r="4" t="181" w="191" /><ent r="3" t="181" w="217" /><ent r="3" t="181" w="217" /><ent r="3" t="181" w="224" /><ent r="3" t="181" w="224" /><ent r="5" t="182" w="75" /><ent r="5" t="182" w="75" /><ent r="4" t="182" w="91" /><ent r="4" t="182" w="91" /><ent r="5" t="182" w="111" /><ent r="5" t="182" w="111" /><ent r="4" t="182" w="124" /><ent r="4" t="182" w="124" /><ent r="4" t="182" w="184" /><ent r="4" t="182" w="184" /><ent r="4" t="182" w="196" /><ent r="4" t="182" w="196" /><ent r="5" t="182" w="210" /><ent r="5" t="182" w="210" /><ent r="4" t="182" w="237" /><ent r="4" t="182" w="237" /><ent r="4" t="182" w="246" /><ent r="4" t="182" w="246" /><ent r="3" t="183" w="71" /><ent r="3" t="183" w="71" /><ent r="3" t="183" w="83" /><ent r="3" t="183" w="83" /><ent r="3" t="183" w="97" /><ent r="3" t="183" w="97" /><ent r="6" t="183" w="163" /><ent r="6" t="183" w="163" /><ent r="5" t="183" w="192" /><ent r="5" t="183" w="192" /><ent r="12" t="183" w="266" /><ent r="12" t="183" w="266" /><ent r="12" t="183" w="283" /><ent r="12" t="183" w="283" /><ent r="5" t="183" w="412" /><ent r="5" t="183" w="412" /><ent r="5" t="183" w="493" /><ent r="5" t="183" w="493" /><ent r="12" t="183" w="569" /><ent r="12" t="183" w="569" /><ent r="12" t="183" w="586" /><ent r="12" t="183" w="586" /><ent r="100" t="184" w="5" /><ent r="100" t="184" w="5" /><ent r="3" t="184" w="14" /><ent r="3" t="184" w="14" /><ent r="3" t="184" w="50" /><ent r="3" t="184" w="50" /><ent r="3" t="184" w="53" /><ent r="3" t="184" w="53" /><ent r="3" t="184" w="58" /><ent r="3" t="184" w="58" /><ent r="3" t="184" w="89" /><ent r="3" t="184" w="89" /><ent r="3" t="184" w="110" /><ent r="3" t="184" w="110" /><ent r="3" t="184" w="130" /><ent r="3" t="184" w="130" /><ent r="3" t="184" w="198" /><ent r="3" t="184" w="198" /><ent r="5" t="184" w="358" /><ent r="5" t="184" w="358" /><ent r="5" t="184" w="377" /><ent r="5" t="184" w="377" /><ent r="5" t="184" w="403" /><ent r="5" t="184" w="403" /><ent r="100" t="185" w="4" /><ent r="100" t="185" w="4" /><ent r="3" t="185" w="12" /><ent r="3" t="185" w="12" /><ent r="3" t="185" w="20" /><ent r="3" t="185" w="20" /><ent r="3" t="185" w="32" /><ent r="3" t="185" w="32" /><ent r="3" t="185" w="50" /><ent r="3" t="185" w="50" /><ent r="3" t="185" w="59" /><ent r="3" t="185" w="59" /><ent r="3" t="185" w="75" /><ent r="3" t="185" w="75" /><ent r="3" t="186" w="179" /><ent r="3" t="186" w="179" /><ent r="3" t="186" w="187" /><ent r="3" t="186" w="187" /><ent r="3" t="186" w="203" /><ent r="3" t="186" w="203" /><ent r="3" t="186" w="218" /><ent r="3" t="186" w="218" /><ent r="3" t="186" w="227" /><ent r="3" t="186" w="227" /><ent r="5" t="186" w="249" /><ent r="5" t="186" w="249" /><ent r="5" t="186" w="264" /><ent r="5" t="186" w="264" /><ent r="5" t="186" w="293" /><ent r="5" t="186" w="293" /><ent r="3" t="186" w="297" /><ent r="3" t="186" w="297" /><ent r="3" t="186" w="775" /><ent r="3" t="186" w="775" /><ent r="3" t="186" w="847" /><ent r="3" t="186" w="847" /><ent r="3" t="186" w="860" /><ent r="3" t="186" w="860" /><ent r="3" t="186" w="885" /><ent r="3" t="186" w="885" /><ent r="3" t="186" w="910" /><ent r="3" t="186" w="910" /><ent r="3" t="186" w="920" /><ent r="3" t="186" w="920" /><ent r="3" t="186" w="930" /><ent r="3" t="186" w="930" /><ent r="3" t="186" w="936" /><ent r="3" t="186" w="936" /><ent r="5" t="390" w="131" /><ent r="5" t="390" w="131" /></phr><phr n="Fulfilled"><ent r="10" t="73" w="1212" /><ent r="10" t="73" w="1212" /><ent r="4" t="186" w="947" /><ent r="4" t="186" w="947" /><ent r="5" t="189" w="69" /><ent r="5" t="189" w="69" /><ent r="11" t="295" w="1801" /><ent r="11" t="295" w="1801" /><ent r="10" t="391" w="106" /><ent r="9" t="713" w="60" /><ent r="9" t="713" w="60" /><ent r="9" t="713" w="102" /><ent r="9" t="713" w="102" /><ent r="9" t="713" w="116" /><ent r="9" t="713" w="116" /><ent r="9" t="713" w="123" /><ent r="9" t="713" w="123" /><ent r="9" t="713" w="213" /><ent r="9" t="713" w="213" /><ent r="9" t="713" w="264" /><ent r="9" t="713" w="264" /><ent r="9" t="713" w="314" /><ent r="9" t="713" w="314" /><ent r="9" t="713" w="382" /><ent r="9" t="713" w="382" /><ent r="9" t="715" w="1312" /><ent r="9" t="715" w="1312" /></phr><phr n="Fulfill"><ent r="6" t="165" w="1674" /><ent r="6" t="165" w="1674" /><ent r="8" t="165" w="1687" /><ent r="8" t="165" w="1687" /><ent r="1000" t="186" w="1" /><ent r="1000" t="186" w="1" /><ent r="102" t="186" w="11" /><ent r="102" t="186" w="11" /><ent r="6" t="386" w="760" /><ent r="6" t="386" w="760" /><ent r="67" t="717" w="544" /><ent r="67" t="717" w="544" /></phr><phr n="fulfilling"><ent r="3" t="183" w="39" /><ent r="3" t="183" w="39" /><ent r="5" t="184" w="395" /><ent r="5" t="184" w="395" /><ent r="100" t="186" w="7" /><ent r="100" t="186" w="7" /><ent r="9" t="245" w="219" /><ent r="9" t="245" w="219" /><ent r="6" t="419" w="829" /><ent r="6" t="419" w="829" /></phr></stem><stem n="here"><phr n="here"><ent r="5" t="6" w="170" /><ent r="5" t="6" w="170" /><ent r="10" t="24" w="405" /><ent r="10" t="24" w="405" /><ent r="7" t="28" w="394" /><ent r="5" t="31" w="664" /><ent r="5" t="31" w="664" /><ent r="5" t="31" w="705" /><ent r="5" t="31" w="705" /><ent r="5" t="91" w="250" /><ent r="7" t="98" w="299" /><ent r="7" t="98" w="299" /><ent r="5" t="127" w="714" /><ent r="10" t="130" w="203" /><ent r="10" t="130" w="203" /><ent r="5" t="152" w="1126" /><ent r="5" t="152" w="1126" /><ent r="8" t="153" w="1543" /><ent r="8" t="153" w="1543" /><ent r="6" t="156" w="25" /><ent r="6" t="156" w="25" /><ent r="10" t="167" w="1024" /><ent r="10" t="167" w="1132" /><ent r="10" t="167" w="1132" /><ent r="8" t="168" w="705" /><ent r="8" t="168" w="705" /><ent r="7" t="175" w="381" /><ent r="7" t="175" w="381" /><ent r="7" t="175" w="430" /><ent r="7" t="175" w="430" /><ent r="7" t="175" w="534" /><ent r="7" t="175" w="534" /><ent r="7" t="175" w="1608" /><ent r="7" t="175" w="1608" /><ent r="7" t="175" w="1896" /><ent r="7" t="175" w="1952" /><ent r="5" t="176" w="376" /><ent r="5" t="176" w="376" /><ent r="5" t="176" w="417" /><ent r="7" t="177" w="217" /><ent r="7" t="177" w="217" /><ent r="6" t="183" w="128" /><ent r="5" t="184" w="367" /><ent r="5" t="184" w="367" /><ent r="5" t="184" w="390" /><ent r="5" t="184" w="390" /><ent r="3" t="186" w="222" /><ent r="3" t="186" w="222" /><ent r="5" t="186" w="352" /><ent r="5" t="186" w="352" /><ent r="5" t="193" w="100" /><ent r="5" t="193" w="155" /><ent r="5" t="194" w="1068" /><ent r="5" t="194" w="1074" /><ent r="5" t="194" w="1074" /><ent r="5" t="194" w="1151" /><ent r="5" t="194" w="1157" /><ent r="5" t="194" w="1157" /><ent r="5" t="200" w="937" /><ent r="6" t="204" w="122" /><ent r="6" t="204" w="122" /><ent r="3" t="211" w="49" /><ent r="5" t="234" w="545" /><ent r="5" t="234" w="545" /><ent r="5" t="234" w="595" /><ent r="5" t="234" w="595" /><ent r="5" t="234" w="645" /><ent r="5" t="234" w="645" /><ent r="7" t="259" w="1391" /><ent r="7" t="259" w="1391" /><ent r="7" t="259" w="1564" /><ent r="7" t="259" w="1564" /><ent r="10" t="260" w="754" /><ent r="10" t="260" w="783" /><ent r="5" t="262" w="806" /><ent r="8" t="270" w="679" /><ent r="8" t="270" w="679" /><ent r="7" t="270" w="808" /><ent r="7" t="270" w="808" /><ent r="7" t="270" w="824" /><ent r="7" t="270" w="824" /><ent r="3" t="295" w="33" /><ent r="3" t="295" w="33" /><ent r="10" t="309" w="218" /><ent r="10" t="309" w="218" /><ent r="8" t="369" w="2717" /><ent r="8" t="369" w="2717" /><ent r="10" t="384" w="498" /><ent r="8" t="384" w="802" /><ent r="8" t="384" w="802" /><ent r="7" t="396" w="721" /><ent r="7" t="396" w="721" /><ent r="3" t="398" w="32" /><ent r="5" t="403" w="772" /><ent r="5" t="403" w="772" /><ent r="5" t="423" w="2512" /><ent r="6" t="445" w="171" /><ent r="8" t="459" w="534" /><ent r="8" t="462" w="542" /><ent r="13" t="481" w="2384" /><ent r="13" t="481" w="2384" /><ent r="7" t="503" w="333" /><ent r="5" t="515" w="663" /><ent r="5" t="515" w="752" /><ent r="8" t="592" w="123" /><ent r="8" t="592" w="123" /><ent r="3" t="680" w="64" /></phr><phr n="Here"><ent r="5" t="107" w="312" /><ent r="8" t="165" w="1497" /><ent r="8" t="165" w="1497" /><ent r="6" t="270" w="775" /><ent r="6" t="270" w="775" /><ent r="5" t="325" w="1008" /><ent r="7" t="335" w="2839" /><ent r="7" t="335" w="2839" /><ent r="3" t="421" w="34" /><ent r="3" t="421" w="34" /><ent r="5" t="423" w="977" /><ent r="3" t="423" w="2073" /><ent r="5" t="515" w="648" /><ent r="5" t="515" w="648" /><ent r="5" t="515" w="1067" /><ent r="5" t="515" w="1067" /><ent r="5" t="515" w="1082" /></phr></stem><stem n="two-tier"><phr n="two-tier"><ent r="5" t="6" w="179" /><ent r="5" t="6" w="179" /></phr></stem><stem n="two"><phr n="two"><ent r="5" t="6" w="179" /><ent r="3" t="12" w="10" /><ent r="3" t="12" w="10" /><ent r="3" t="28" w="42" /><ent r="3" t="28" w="42" /><ent r="5" t="28" w="370" /><ent r="5" t="28" w="370" /><ent r="3" t="31" w="43" /><ent r="3" t="31" w="43" /><ent r="3" t="37" w="82" /><ent r="3" t="37" w="82" /><ent r="3" t="46" w="66" /><ent r="3" t="46" w="66" /><ent r="7" t="80" w="346" /><ent r="7" t="80" w="346" /><ent r="7" t="80" w="894" /><ent r="7" t="80" w="894" /><ent r="7" t="80" w="1451" /><ent r="7" t="80" w="1451" /><ent r="3" t="83" w="18" /><ent r="3" t="83" w="18" /><ent r="5" t="84" w="904" /><ent r="5" t="84" w="904" /><ent r="5" t="93" w="335" /><ent r="5" t="93" w="335" /><ent r="7" t="100" w="165" /><ent r="7" t="100" w="165" /><ent r="3" t="104" w="86" /><ent r="3" t="104" w="86" /><ent r="5" t="106" w="163" /><ent r="5" t="106" w="163" /><ent r="5" t="124" w="3760" /><ent r="5" t="124" w="3760" /><ent r="5" t="124" w="4689" /><ent r="5" t="124" w="4689" /><ent r="5" t="138" w="968" /><ent r="5" t="138" w="968" /><ent r="5" t="145" w="240" /><ent r="5" t="145" w="240" /><ent r="3" t="160" w="167" /><ent r="3" t="160" w="167" /><ent r="5" t="168" w="2011" /><ent r="3" t="184" w="140" /><ent r="3" t="184" w="140" /><ent r="3" t="186" w="300" /><ent r="3" t="186" w="300" /><ent r="3" t="194" w="60" /><ent r="3" t="194" w="60" /><ent r="3" t="194" w="409" /><ent r="3" t="194" w="409" /><ent r="5" t="194" w="489" /><ent r="5" t="194" w="489" /><ent r="5" t="242" w="1337" /><ent r="5" t="242" w="1337" /><ent r="7" t="243" w="671" /><ent r="7" t="243" w="671" /><ent r="7" t="243" w="1852" /><ent r="7" t="243" w="1852" /><ent r="7" t="243" w="2257" /><ent r="7" t="243" w="2257" /><ent r="5" t="257" w="906" /><ent r="5" t="257" w="906" /><ent r="6" t="257" w="1016" /><ent r="6" t="257" w="1016" /><ent r="7" t="259" w="1569" /><ent r="7" t="259" w="1569" /><ent r="11" t="260" w="1919" /><ent r="11" t="260" w="1919" /><ent r="5" t="263" w="7338" /><ent r="5" t="263" w="7338" /><ent r="3" t="266" w="208" /><ent r="3" t="266" w="208" /><ent r="3" t="269" w="158" /><ent r="3" t="269" w="158" /><ent r="3" t="270" w="122" /><ent r="3" t="270" w="122" /><ent r="8" t="278" w="640" /><ent r="8" t="278" w="640" /><ent r="3" t="283" w="12" /><ent r="3" t="283" w="12" /><ent r="12" t="283" w="1089" /><ent r="12" t="283" w="1089" /><ent r="12" t="283" w="1153" /><ent r="12" t="283" w="1153" /><ent r="12" t="283" w="1166" /><ent r="12" t="283" w="1166" /><ent r="11" t="283" w="1510" /><ent r="11" t="283" w="1510" /><ent r="4" t="285" w="204" /><ent r="4" t="285" w="204" /><ent r="5" t="292" w="587" /><ent r="5" t="292" w="587" /><ent r="5" t="292" w="909" /><ent r="5" t="292" w="909" /><ent r="5" t="292" w="981" /><ent r="5" t="292" w="981" /><ent r="12" t="295" w="4406" /><ent r="12" t="295" w="4406" /><ent r="12" t="295" w="4422" /><ent r="12" t="295" w="4422" /><ent r="3" t="311" w="178" /><ent r="3" t="311" w="178" /><ent r="11" t="314" w="1003" /><ent r="9" t="316" w="1069" /><ent r="9" t="316" w="1069" /><ent r="8" t="319" w="391" /><ent r="8" t="319" w="391" /><ent r="5" t="324" w="149" /><ent r="5" t="324" w="149" /><ent r="7" t="325" w="1677" /><ent r="7" t="325" w="1677" /><ent r="5" t="332" w="901" /><ent r="5" t="332" w="901" /><ent r="3" t="363" w="789" /><ent r="3" t="363" w="789" /><ent r="5" t="364" w="669" /><ent r="5" t="364" w="669" /><ent r="9" t="392" w="978" /><ent r="9" t="392" w="978" /><ent r="9" t="426" w="710" /><ent r="9" t="426" w="710" /><ent r="5" t="433" w="167" /><ent r="5" t="433" w="167" /><ent r="13" t="455" w="1494" /><ent r="13" t="455" w="1494" /><ent r="11" t="457" w="845" /><ent r="11" t="457" w="845" /><ent r="11" t="469" w="319" /><ent r="11" t="469" w="319" /><ent r="3" t="473" w="19" /><ent r="3" t="473" w="19" /><ent r="9" t="481" w="2855" /><ent r="9" t="481" w="2855" /><ent r="5" t="481" w="3660" /><ent r="5" t="481" w="3660" /><ent r="5" t="481" w="3739" /><ent r="5" t="481" w="3739" /><ent r="3" t="486" w="45" /><ent r="3" t="486" w="45" /><ent r="6" t="514" w="936" /><ent r="6" t="514" w="936" /><ent r="5" t="514" w="1079" /><ent r="5" t="514" w="1079" /><ent r="3" t="517" w="571" /><ent r="3" t="517" w="571" /><ent r="5" t="518" w="1409" /><ent r="5" t="518" w="1409" /><ent r="5" t="518" w="1711" /><ent r="5" t="518" w="1711" /><ent r="3" t="597" w="42" /><ent r="3" t="597" w="42" /><ent r="3" t="597" w="283" /><ent r="3" t="597" w="283" /><ent r="3" t="597" w="342" /><ent r="3" t="597" w="342" /><ent r="3" t="606" w="19" /><ent r="3" t="606" w="19" /><ent r="3" t="607" w="116" /><ent r="3" t="607" w="116" /><ent r="3" t="607" w="145" /><ent r="3" t="607" w="145" /><ent r="3" t="626" w="21" /><ent r="3" t="626" w="21" /><ent r="3" t="633" w="78" /><ent r="3" t="633" w="78" /><ent r="6" t="634" w="74" /><ent r="6" t="634" w="74" /><ent r="5" t="647" w="1543" /><ent r="5" t="647" w="1543" /><ent r="3" t="654" w="13" /><ent r="3" t="654" w="13" /></phr><phr n="Two"><ent r="7" t="124" w="924" /><ent r="7" t="124" w="924" /><ent r="8" t="215" w="1266" /><ent r="8" t="215" w="1266" /><ent r="7" t="243" w="685" /><ent r="7" t="243" w="685" /><ent r="7" t="329" w="1061" /><ent r="7" t="329" w="1061" /><ent r="5" t="514" w="129" /><ent r="5" t="514" w="129" /><ent r="3" t="704" w="17" /><ent r="3" t="704" w="17" /><ent r="3" t="704" w="364" /><ent r="3" t="704" w="364" /></phr></stem></index>